cuckoo/__init__.py
cuckoo/base.py
cuckoo/datasource/coingecko.py
cuckoo/datasource/geckoterminal.py
cuckoo/handler/checker_handler.py
cuckoo/handler/handler_manager.py
cuckoo/handler/watcher_handler.py
cuckoo/messenger/console_sender.py
cuckoo/messenger/email_sender.py
cuckoo/messenger/gmail_sender.py
cuckoo/messenger/messenger_manager.py
cuckoo/processor/simple_processor.py
cuckoo/tracker/__init__.py
cuckoo/tracker/coingecko_tracker.py
cuckoo/tracker/geckoterminal_tracker.py
cuckoo/tracker/token_tracker.py
cuckoo/utils/__init__.py
cuckoo/utils/request_helper.py
t2og_cuckoo-0.0.4b4.dist-info/LICENSE
t2og_cuckoo-0.0.4b4.dist-info/METADATA
t2og_cuckoo-0.0.4b4.dist-info/WHEEL
t2og_cuckoo-0.0.4b4.dist-info/entry_points.txt
t2og_cuckoo-0.0.4b4.dist-info/top_level.txt
t2og_cuckoo-0.0.4b4.dist-info/RECORD
