Metadata-Version: 2.1
Name: t2og-cuckoo
Version: 0.0.4b4
Author: t2og
License: MIT License
Project-URL: Homepage, https://github.com/t2og/cuckoo
Project-URL: Repository, https://github.com/t2og/cuckoo.git
Requires-Python: >=3.10
License-File: LICENSE
Requires-Dist: requests
Requires-Dist: python-dotenv
Requires-Dist: PyYAML
Requires-Dist: google-api-python-client
Requires-Dist: google-auth-httplib2
Requires-Dist: google-auth-oauthlib
